rfsdk/__init__.py
rfsdk/account_req_helper.py
rfsdk/comm_utils.py
rfsdk/gateway.py
rfsdk/instrument.json
rfsdk/quote_req_helper.py
rfsdk/rpc.ini
rfsdk/service_method.py
rfsdk/station.json
rfsdk/trade_client.py
rfsdk/trade_req_helper.py
rfsdk/protocol/__init__.py
rfsdk/protocol/common_pb2.py
rfsdk/protocol/quote/__init__.py
rfsdk/protocol/quote/mdsquote_pb2.py
rfsdk/protocol/quote/quote_enum_pb2.py
rfsdk/protocol/quote/quote_pb2.py
rfsdk/protocol/trade/__init__.py
rfsdk/protocol/trade/trade_enum_pb2.py
rfsdk/protocol/trade/trade_futures_pb2.py
rfsdk/protocol/trade/trade_pb2.py
rfsdk/protocol/trade/trade_stock_pb2.py
rfsdk/pyant/__init__.py
rfsdk/pyant/ant_rpc.cp38-win_amd64.pyd
rfsdk/pyant/rpc_call_helper.py
package_test_czh-0.1.12.dist-info/LICENSE
package_test_czh-0.1.12.dist-info/METADATA
package_test_czh-0.1.12.dist-info/WHEEL
package_test_czh-0.1.12.dist-info/top_level.txt
package_test_czh-0.1.12.dist-info/RECORD
